odoo/addons/fleet_vehicle_service_services/README.rst
odoo/addons/fleet_vehicle_service_services/__init__.py
odoo/addons/fleet_vehicle_service_services/__manifest__.py
odoo/addons/fleet_vehicle_service_services/i18n/es.po
odoo/addons/fleet_vehicle_service_services/i18n/fleet_vehicle_service_services.pot
odoo/addons/fleet_vehicle_service_services/i18n/it.po
odoo/addons/fleet_vehicle_service_services/i18n/pt_BR.po
odoo/addons/fleet_vehicle_service_services/i18n/sv.po
odoo/addons/fleet_vehicle_service_services/models/__init__.py
odoo/addons/fleet_vehicle_service_services/models/fleet_vehicle_cost.py
odoo/addons/fleet_vehicle_service_services/readme/CONTRIBUTORS.md
odoo/addons/fleet_vehicle_service_services/readme/DESCRIPTION.md
odoo/addons/fleet_vehicle_service_services/static/description/icon.png
odoo/addons/fleet_vehicle_service_services/static/description/index.html
odoo/addons/fleet_vehicle_service_services/views/fleet_vehicle_cost_views.xml
odoo_addon_fleet_vehicle_service_services-18.0.1.0.0.2.dist-info/METADATA
odoo_addon_fleet_vehicle_service_services-18.0.1.0.0.2.dist-info/WHEEL
odoo_addon_fleet_vehicle_service_services-18.0.1.0.0.2.dist-info/top_level.txt
odoo_addon_fleet_vehicle_service_services-18.0.1.0.0.2.dist-info/RECORD
